{"trial_id": "0", "hyperparameters": {"space": [{"class_name": "Choice", "config": {"name": "units", "default": 16, "conditions": [], "values": [16, 32], "ordered": true}}, {"class_name": "Choice", "config": {"name": "Dropout_rate", "default": 0.1, "conditions": [], "values": [0.1, 0.2], "ordered": true}}, {"class_name": "Choice", "config": {"name": "learning_rate", "default": 0.1, "conditions": [], "values": [0.1, 0.01], "ordered": true}}], "values": {"units": 16, "Dropout_rate": 0.1, "learning_rate": 0.1}}, "metrics": {"metrics": {"loss": {"direction": "min", "observations": [{"value": [0.7816783785820007], "step": 4}]}, "accuracy": {"direction": "max", "observations": [{"value": [0.6715801954269409], "step": 4}]}, "val_loss": {"direction": "min", "observations": [{"value": [0.7473262548446655], "step": 4}]}, "val_accuracy": {"direction": "max", "observations": [{"value": [0.7688679099082947], "step": 4}]}}}, "score": 0.7688679099082947, "best_step": 4, "status": "COMPLETED", "message": null}